{"v":"4.8.0","ip":0,"op":175,"fr":25,"w":500,"h":500,"nm":"docs","assets":[],"layers":[{"ind":1,"ty":3,"nm":"Null 24","sr":1,"ks":{"o":{"a":0,"k":0},"r":{"a":0,"k":0},"p":{"a":0,"k":[250,448,0]},"a":{"a":0,"k":[0,0,0]},"s":{"a":0,"k":[100,100,100],"x":"var $bm_rt;\nvar n, t, n, t, amp, freq, decay, angle, scaleFact;\nn = 0;\nt = 0;\nif (marker.numKeys > 0) {\n    n = marker.nearestKey(time).index;\n    if (marker.key(n).time > time)\n        n--;\n}\nif (n > 0)\n    t = $bm_sub(time, marker.key(n).time);\namp = 10;\nfreq = 3;\ndecay = 4;\nangle = $bm_mul($bm_mul($bm_mul(freq, 2), Math.PI), t);\nscaleFact = $bm_div($bm_sum(100, $bm_div($bm_mul(amp, Math.sin(angle)), Math.exp($bm_mul(decay, t)))), 100);\n$bm_rt = [\n    value[0] * scaleFact,\n    value[1] / scaleFact\n];"}},"ip":0,"op":175,"st":0},{"ind":2,"ty":4,"nm":"244[B]_07_S_docs Outlines","sr":1,"ks":{"o":{"a":0,"k":100},"r":{"a":0,"k":0},"p":{"a":0,"k":[-9.79,-59.526,0]},"a":{"a":0,"k":[56,25,0]},"s":{"k":[{"i":{"x":[0.833,0.833,0.833],"y":[0.833,0.833,0.833]},"o":{"x":[0.167,0.167,0.167],"y":[0.167,0.167,0.167]},"t":6,"s":[0,0,100]},{"t":11,"s":[186.485,214.494,100]}],"x":"var $bm_rt;\nvar amp, freq, decay, n, n, t, t, v;\namp = 0.05;\nfreq = 3;\ndecay = 7;\n$bm_rt = n = 0;\nif (numKeys > 0) {\n    $bm_rt = n = nearestKey(time).index;\n    if (key(n).time > time) {\n        n--;\n    }\n}\nif (n == 0) {\n    $bm_rt = t = 0;\n} else {\n    $bm_rt = t = $bm_sub(time, key(n).time);\n}\nif (n > 0) {\n    v = velocityAtTime($bm_sub(key(n).time, $bm_div(thisComp.frameDuration, 10)));\n    $bm_rt = $bm_sum(value, $bm_div($bm_mul($bm_mul(v, amp), Math.sin($bm_mul($bm_mul($bm_mul(freq, t), 2), Math.PI))), Math.exp($bm_mul(decay, t))));\n} else {\n    $bm_rt = value;\n}","a":1}},"shapes":[{"ty":"gr","nm":"Group 1","bm":0,"mn":"ADBE Vector Group","it":[{"ty":"sh","nm":"Path 1","mn":"ADBE Vector Shape - Group","ind":0,"ks":{"k":{"i":[[0,0],[0,0]],"o":[[0,0],[0,0]],"v":[[25,25],[87,25]],"c":false},"a":0}},{"ty":"st","nm":"Stroke 1","bm":0,"mn":"ADBE Vector Graphic - Stroke","lc":1,"lj":2,"o":{"a":0,"k":100},"w":{"a":0,"k":10},"c":{"a":0,"k":[0.7529411764705882,0.7529411764705882,0.7529411764705882,1]}},{"ty":"tr","o":{"a":0,"k":100},"r":{"a":0,"k":0},"p":{"a":0,"k":[0,0]},"a":{"a":0,"k":[0,0]},"s":{"a":0,"k":[100,100]},"nm":"Transform","sk":{"a":0,"k":0},"sa":{"a":0,"k":0}}]}],"ip":6,"op":175,"st":6,"parent":1},{"ind":3,"ty":4,"nm":"244[B]_06_S_docs Outlines","sr":1,"ks":{"o":{"a":0,"k":100},"r":{"a":0,"k":0},"p":{"a":0,"k":[-9.79,-102.425,0]},"a":{"a":0,"k":[56,25,0]},"s":{"k":[{"i":{"x":[0.833,0.833,0.833],"y":[0.833,0.833,0.833]},"o":{"x":[0.167,0.167,0.167],"y":[0.167,0.167,0.167]},"t":5,"s":[0,0,100]},{"t":10,"s":[186.485,214.494,100]}],"x":"var $bm_rt;\nvar amp, freq, decay, n, n, t, t, v;\namp = 0.05;\nfreq = 3;\ndecay = 7;\n$bm_rt = n = 0;\nif (numKeys > 0) {\n    $bm_rt = n = nearestKey(time).index;\n    if (key(n).time > time) {\n        n--;\n    }\n}\nif (n == 0) {\n    $bm_rt = t = 0;\n} else {\n    $bm_rt = t = $bm_sub(time, key(n).time);\n}\nif (n > 0) {\n    v = velocityAtTime($bm_sub(key(n).time, $bm_div(thisComp.frameDuration, 10)));\n    $bm_rt = $bm_sum(value, $bm_div($bm_mul($bm_mul(v, amp), Math.sin($bm_mul($bm_mul($bm_mul(freq, t), 2), Math.PI))), Math.exp($bm_mul(decay, t))));\n} else {\n    $bm_rt = value;\n}","a":1}},"shapes":[{"ty":"gr","nm":"Group 1","bm":0,"mn":"ADBE Vector Group","it":[{"ty":"sh","nm":"Path 1","mn":"ADBE Vector Shape - Group","ind":0,"ks":{"k":{"i":[[0,0],[0,0]],"o":[[0,0],[0,0]],"v":[[25,25],[87,25]],"c":false},"a":0}},{"ty":"st","nm":"Stroke 1","bm":0,"mn":"ADBE Vector Graphic - Stroke","lc":1,"lj":2,"o":{"a":0,"k":100},"w":{"a":0,"k":10},"c":{"a":0,"k":[1,0.8431372549019608,0,1]}},{"ty":"tr","o":{"a":0,"k":100},"r":{"a":0,"k":0},"p":{"a":0,"k":[0,0]},"a":{"a":0,"k":[0,0]},"s":{"a":0,"k":[100,100]},"nm":"Transform","sk":{"a":0,"k":0},"sa":{"a":0,"k":0}}]}],"ip":5,"op":175,"st":5,"parent":1},{"ind":4,"ty":4,"nm":"244[B]_05_S_docs Outlines","sr":1,"ks":{"o":{"a":0,"k":100},"r":{"a":0,"k":0},"p":{"a":0,"k":[-9.79,-145.324,0]},"a":{"a":0,"k":[56,25,0]},"s":{"k":[{"i":{"x":[0.833,0.833,0.833],"y":[0.833,0.833,0.833]},"o":{"x":[0.167,0.167,0.167],"y":[0.167,0.167,0.167]},"t":4,"s":[0,0,100]},{"t":9,"s":[186.485,214.494,100]}],"x":"var $bm_rt;\nvar amp, freq, decay, n, n, t, t, v;\namp = 0.05;\nfreq = 3;\ndecay = 7;\n$bm_rt = n = 0;\nif (numKeys > 0) {\n    $bm_rt = n = nearestKey(time).index;\n    if (key(n).time > time) {\n        n--;\n    }\n}\nif (n == 0) {\n    $bm_rt = t = 0;\n} else {\n    $bm_rt = t = $bm_sub(time, key(n).time);\n}\nif (n > 0) {\n    v = velocityAtTime($bm_sub(key(n).time, $bm_div(thisComp.frameDuration, 10)));\n    $bm_rt = $bm_sum(value, $bm_div($bm_mul($bm_mul(v, amp), Math.sin($bm_mul($bm_mul($bm_mul(freq, t), 2), Math.PI))), Math.exp($bm_mul(decay, t))));\n} else {\n    $bm_rt = value;\n}","a":1}},"shapes":[{"ty":"gr","nm":"Group 1","bm":0,"mn":"ADBE Vector Group","it":[{"ty":"sh","nm":"Path 1","mn":"ADBE Vector Shape - Group","ind":0,"ks":{"k":{"i":[[0,0],[0,0]],"o":[[0,0],[0,0]],"v":[[25,25],[87,25]],"c":false},"a":0}},{"ty":"st","nm":"Stroke 1","bm":0,"mn":"ADBE Vector Graphic - Stroke","lc":1,"lj":2,"o":{"a":0,"k":100},"w":{"a":0,"k":10},"c":{"a":0,"k":[0.7529411764705882,0.7529411764705882,0.7529411764705882,1]}},{"ty":"tr","o":{"a":0,"k":100},"r":{"a":0,"k":0},"p":{"a":0,"k":[0,0]},"a":{"a":0,"k":[0,0]},"s":{"a":0,"k":[100,100]},"nm":"Transform","sk":{"a":0,"k":0},"sa":{"a":0,"k":0}}]}],"ip":4,"op":175,"st":4,"parent":1},{"ind":5,"ty":4,"nm":"244[B]_04_S_docs Outlines","sr":1,"ks":{"o":{"a":0,"k":100},"r":{"a":0,"k":0},"p":{"a":0,"k":[-9.79,-188.223,0]},"a":{"a":0,"k":[56,25,0]},"s":{"k":[{"i":{"x":[0.833,0.833,0.833],"y":[0.833,0.833,0.833]},"o":{"x":[0.167,0.167,0.167],"y":[0.167,0.167,0.167]},"t":3,"s":[0,0,100]},{"t":8,"s":[186.485,214.494,100]}],"x":"var $bm_rt;\nvar amp, freq, decay, n, n, t, t, v;\namp = 0.05;\nfreq = 3;\ndecay = 7;\n$bm_rt = n = 0;\nif (numKeys > 0) {\n    $bm_rt = n = nearestKey(time).index;\n    if (key(n).time > time) {\n        n--;\n    }\n}\nif (n == 0) {\n    $bm_rt = t = 0;\n} else {\n    $bm_rt = t = $bm_sub(time, key(n).time);\n}\nif (n > 0) {\n    v = velocityAtTime($bm_sub(key(n).time, $bm_div(thisComp.frameDuration, 10)));\n    $bm_rt = $bm_sum(value, $bm_div($bm_mul($bm_mul(v, amp), Math.sin($bm_mul($bm_mul($bm_mul(freq, t), 2), Math.PI))), Math.exp($bm_mul(decay, t))));\n} else {\n    $bm_rt = value;\n}","a":1}},"shapes":[{"ty":"gr","nm":"Group 1","bm":0,"mn":"ADBE Vector Group","it":[{"ty":"sh","nm":"Path 1","mn":"ADBE Vector Shape - Group","ind":0,"ks":{"k":{"i":[[0,0],[0,0]],"o":[[0,0],[0,0]],"v":[[25,25],[87,25]],"c":false},"a":0}},{"ty":"st","nm":"Stroke 1","bm":0,"mn":"ADBE Vector Graphic - Stroke","lc":1,"lj":2,"o":{"a":0,"k":100},"w":{"a":0,"k":10},"c":{"a":0,"k":[1,0.8431372549019608,0,1]}},{"ty":"tr","o":{"a":0,"k":100},"r":{"a":0,"k":0},"p":{"a":0,"k":[0,0]},"a":{"a":0,"k":[0,0]},"s":{"a":0,"k":[100,100]},"nm":"Transform","sk":{"a":0,"k":0},"sa":{"a":0,"k":0}}]}],"ip":3,"op":175,"st":3,"parent":1},{"ind":6,"ty":4,"nm":"244[B]_03_S_docs Outlines","sr":1,"ks":{"o":{"a":0,"k":100},"r":{"a":0,"k":0},"p":{"a":0,"k":[52.216,-198.412,0]},"a":{"a":0,"k":[68.5,79,0]},"s":{"k":[{"i":{"x":[0.833,0.833,0.833],"y":[0.833,0.833,0.833]},"o":{"x":[0.167,0.167,0.167],"y":[0.167,0.167,0.167]},"t":2,"s":[0,0,100]},{"t":7,"s":[186.485,214.494,100]}],"x":"var $bm_rt;\nvar amp, freq, decay, n, n, t, t, v;\namp = 0.05;\nfreq = 3;\ndecay = 7;\n$bm_rt = n = 0;\nif (numKeys > 0) {\n    $bm_rt = n = nearestKey(time).index;\n    if (key(n).time > time) {\n        n--;\n    }\n}\nif (n == 0) {\n    $bm_rt = t = 0;\n} else {\n    $bm_rt = t = $bm_sub(time, key(n).time);\n}\nif (n > 0) {\n    v = velocityAtTime($bm_sub(key(n).time, $bm_div(thisComp.frameDuration, 10)));\n    $bm_rt = $bm_sum(value, $bm_div($bm_mul($bm_mul(v, amp), Math.sin($bm_mul($bm_mul($bm_mul(freq, t), 2), Math.PI))), Math.exp($bm_mul(decay, t))));\n} else {\n    $bm_rt = value;\n}","a":1}},"shapes":[{"ty":"gr","nm":"Group 1","bm":0,"mn":"ADBE Vector Group","it":[{"ty":"sh","nm":"Path 1","mn":"ADBE Vector Shape - Group","ind":0,"ks":{"k":{"i":[[0,0],[0,0],[0,0],[0,0],[0,0]],"o":[[0,0],[0,0],[0,0],[0,0],[0,0]],"v":[[-43.5,-45.25],[-43.5,-54],[43.5,-54],[43.5,54],[35,54]],"c":false},"a":0}},{"ty":"st","nm":"Stroke 1","bm":0,"mn":"ADBE Vector Graphic - Stroke","lc":1,"lj":2,"o":{"a":0,"k":100},"w":{"a":0,"k":10},"c":{"a":0,"k":[0.7490196078431373,0.7490196078431373,0.7490196078431373,1]}},{"ty":"tr","o":{"a":0,"k":100},"r":{"a":0,"k":0},"p":{"a":0,"k":[68.5,79]},"a":{"a":0,"k":[0,0]},"s":{"a":0,"k":[100,100]},"nm":"Transform","sk":{"a":0,"k":0},"sa":{"a":0,"k":0}}]}],"ip":2,"op":175,"st":2,"parent":1},{"ind":7,"ty":4,"nm":"244[B]_02_S_docs Outlines","sr":1,"ks":{"o":{"a":0,"k":100},"r":{"a":0,"k":0},"p":{"a":0,"k":[20.513,-161.947,0]},"a":{"a":0,"k":[68.5,79,0]},"s":{"k":[{"i":{"x":[0.833,0.833,0.833],"y":[0.833,0.833,0.833]},"o":{"x":[0.167,0.167,0.167],"y":[0.167,0.167,0.167]},"t":1,"s":[0,0,100]},{"t":6,"s":[186.485,214.494,100]}],"x":"var $bm_rt;\nvar amp, freq, decay, n, n, t, t, v;\namp = 0.05;\nfreq = 3;\ndecay = 7;\n$bm_rt = n = 0;\nif (numKeys > 0) {\n    $bm_rt = n = nearestKey(time).index;\n    if (key(n).time > time) {\n        n--;\n    }\n}\nif (n == 0) {\n    $bm_rt = t = 0;\n} else {\n    $bm_rt = t = $bm_sub(time, key(n).time);\n}\nif (n > 0) {\n    v = velocityAtTime($bm_sub(key(n).time, $bm_div(thisComp.frameDuration, 10)));\n    $bm_rt = $bm_sum(value, $bm_div($bm_mul($bm_mul(v, amp), Math.sin($bm_mul($bm_mul($bm_mul(freq, t), 2), Math.PI))), Math.exp($bm_mul(decay, t))));\n} else {\n    $bm_rt = value;\n}","a":1}},"shapes":[{"ty":"gr","nm":"Group 1","bm":0,"mn":"ADBE Vector Group","it":[{"ty":"sh","nm":"Path 1","mn":"ADBE Vector Shape - Group","ind":0,"ks":{"k":{"i":[[0,0],[0,0],[0,0],[0,0],[0,0]],"o":[[0,0],[0,0],[0,0],[0,0],[0,0]],"v":[[-43.5,-45.75],[-43.5,-54],[43.5,-54],[43.5,54],[35.5,54]],"c":false},"a":0}},{"ty":"st","nm":"Stroke 1","bm":0,"mn":"ADBE Vector Graphic - Stroke","lc":1,"lj":2,"o":{"a":0,"k":100},"w":{"a":0,"k":10},"c":{"a":0,"k":[1,0.808000033509,0,1]}},{"ty":"tr","o":{"a":0,"k":100},"r":{"a":0,"k":0},"p":{"a":0,"k":[68.5,79]},"a":{"a":0,"k":[0,0]},"s":{"a":0,"k":[100,100]},"nm":"Transform","sk":{"a":0,"k":0},"sa":{"a":0,"k":0}}]}],"ip":1,"op":175,"st":1,"parent":1},{"ind":8,"ty":4,"nm":"244[B]_01_S_docs Outlines","sr":1,"ks":{"o":{"a":0,"k":100},"r":{"a":0,"k":0},"p":{"a":0,"k":[-9.324,-127.627,0]},"a":{"a":0,"k":[68.5,79,0]},"s":{"k":[{"i":{"x":[0.833,0.833,0.833],"y":[0.833,0.833,0.833]},"o":{"x":[0.167,0.167,0.167],"y":[0.167,0.167,0.167]},"t":0,"s":[0,0,100]},{"t":5,"s":[186.485,214.494,100]}],"x":"var $bm_rt;\nvar amp, freq, decay, n, n, t, t, v;\namp = 0.05;\nfreq = 3;\ndecay = 7;\n$bm_rt = n = 0;\nif (numKeys > 0) {\n    $bm_rt = n = nearestKey(time).index;\n    if (key(n).time > time) {\n        n--;\n    }\n}\nif (n == 0) {\n    $bm_rt = t = 0;\n} else {\n    $bm_rt = t = $bm_sub(time, key(n).time);\n}\nif (n > 0) {\n    v = velocityAtTime($bm_sub(key(n).time, $bm_div(thisComp.frameDuration, 10)));\n    $bm_rt = $bm_sum(value, $bm_div($bm_mul($bm_mul(v, amp), Math.sin($bm_mul($bm_mul($bm_mul(freq, t), 2), Math.PI))), Math.exp($bm_mul(decay, t))));\n} else {\n    $bm_rt = value;\n}","a":1}},"shapes":[{"ty":"gr","nm":"Group 1","bm":0,"mn":"ADBE Vector Group","it":[{"ty":"sh","nm":"Path 1","mn":"ADBE Vector Shape - Group","ind":0,"ks":{"k":{"i":[[0,0],[0,0],[0,0],[0,0]],"o":[[0,0],[0,0],[0,0],[0,0]],"v":[[43.5,54],[-43.5,54],[-43.5,-54],[43.5,-54]],"c":true},"a":0}},{"ty":"st","nm":"Stroke 1","bm":0,"mn":"ADBE Vector Graphic - Stroke","lc":1,"lj":2,"o":{"a":0,"k":100},"w":{"a":0,"k":10},"c":{"a":0,"k":[0.7529411764705882,0.7529411764705882,0.7529411764705882,1]}},{"ty":"tr","o":{"a":0,"k":100},"r":{"a":0,"k":0},"p":{"a":0,"k":[68.5,79]},"a":{"a":0,"k":[0,0]},"s":{"a":0,"k":[100,100]},"nm":"Transform","sk":{"a":0,"k":0},"sa":{"a":0,"k":0}}]}],"ip":0,"op":175,"st":0,"parent":1}],"markers":[]}